unique_six/__init__.py
unique_six/client.py
unique_six/exception.py
unique_six/get_creds.sh
unique_six/http_adapter.py
unique_six/schema/__init__.py
unique_six/schema/common/base/__init__.py
unique_six/schema/common/base/model.py
unique_six/schema/common/base/request.py
unique_six/schema/common/base/response.py
unique_six/schema/common/entity.py
unique_six/schema/common/instrument.py
unique_six/schema/common/language.py
unique_six/schema/common/listing.py
unique_six/schema/common/lookup.py
unique_six/schema/common/market.py
unique_six/schema/common/price.py
unique_six/schema/common/security.py
unique_six/schema/end_of_day_history/__init__.py
unique_six/schema/end_of_day_history/request.py
unique_six/schema/end_of_day_history/response.py
unique_six/schema/entity_base/__init__.py
unique_six/schema/entity_base/listing/request.py
unique_six/schema/entity_base/listing/response.py
unique_six/schema/free_text_search/__init__.py
unique_six/schema/free_text_search/entities/__init__.py
unique_six/schema/free_text_search/entities/request.py
unique_six/schema/free_text_search/entities/response.py
unique_six/schema/free_text_search/instruments/__init__.py
unique_six/schema/free_text_search/instruments/request.py
unique_six/schema/free_text_search/instruments/response.py
unique_six/schema/free_text_search/markets/__init__.py
unique_six/schema/free_text_search/markets/request.py
unique_six/schema/free_text_search/markets/response.py
unique_six/schema/intraday_history/__init__.py
unique_six/schema/intraday_history/summary/request.py
unique_six/schema/intraday_history/summary/response.py
unique_six/schema/intraday_snapshot/__init__.py
unique_six/schema/intraday_snapshot/quality_of_service.py
unique_six/schema/intraday_snapshot/request.py
unique_six/schema/intraday_snapshot/response.py
unique_six-0.1.1.dist-info/LICENSE
unique_six-0.1.1.dist-info/METADATA
unique_six-0.1.1.dist-info/WHEEL
unique_six-0.1.1.dist-info/RECORD
