Metadata-Version: 2.3
Name: unique_six
Version: 0.1.1
Summary: Unique Six API client
License: Proprietary
Author: Ahmed Jellouli
Author-email: ahmed.jellouli.ext@unique.ch
Requires-Python: >=3.12,<4.0
Classifier: License :: Other/Proprietary License
Classifier: Programming Language :: Python :: 3
Classifier: Programming Language :: Python :: 3.12
Classifier: Programming Language :: Python :: 3.13
Requires-Dist: cryptography (>=45.0.6,<46.0.0)
Requires-Dist: pydantic (>=2.12.4,<3.0.0)
Requires-Dist: python-dotenv (>=1.0.1,<2.0.0)
Requires-Dist: unique-toolkit (>=1.38.3,<2.0.0)
